{
   "version": 1,
   "commands": [
      {
         "command": "DrawPaint",
         "visible": true,
         "paint": {
            "color": [ 0, 0, 0, 0 ],
            "blendMode": "Src"
         }
      },
      {
         "command": "Save",
         "visible": true
      },
      {
         "command": "Concat44",
         "visible": true,
         "matrix": [
            [ 1, 0, 0, -1177 ],
            [ 0, 1, 0, -1347 ],
            [ 0, 0, 1, 0 ],
            [ 0, 0, 0, 1 ]
         ]
      },
      {
         "command": "DrawRect",
         "visible": true,
         "coords": [ 1177, 1347, 1240, 1438 ],
         "paint": {
            "antiAlias": true,
            "dither": true,
            "shader": {
               "name": "SkLocalMatrixShader",
               "data": "data/0",
               "values": {
                  "00_matrix": [
                     [ 1, 0, 1177 ],
                     [ 0, 1, 1347 ],
                     [ 0, 0, 1 ]
                  ],
                  "01_SkLinearGradient": {
                     "00_uint": 536870913,
                     "01_colorArray": [
                        [ 1, 0.941176, 0.964706, 1 ],
                        [ 1, 0.941176, 0.964706, 1 ]
                     ],
                     "02_byteArray": [
                        "01",
                        "00",
                        "00",
                        "00",
                        "9a",
                        "99",
                        "19",
                        "40",
                        "6e",
                        "a7",
                        "72",
                        "3f",
                        "19",
                        "89",
                        "55",
                        "3d",
                        "91",
                        "83",
                        "9e",
                        "3d",
                        "e6",
                        "ae",
                        "25",
                        "3d",
                        "00",
                        "00",
                        "00",
                        "00",
                        "00",
                        "00",
                        "00",
                        "00",
                        "00",
                        "44",
                        "df",
                        "3e",
                        "00",
                        "32",
                        "c5",
                        "3e",
                        "00",
                        "80",
                        "12",
                        "3e",
                        "00",
                        "d4",
                        "63",
                        "3e",
                        "00",
                        "85",
                        "37",
                        "3f",
                        "00",
                        "40",
                        "78",
                        "3d",
                        "00",
                        "00",
                        "64",
                        "3c",
                        "00",
                        "d0",
                        "c6",
                        "3d",
                        "00",
                        "cf",
                        "36",
                        "3f"
                     ],
                     "03_point": [ 63, 0 ],
                     "04_point": [ 0, 0 ]
                  }
               }
            }
         },
         "shortDesc": " [1177 1347 1240 1438]"
      },
      {
         "command": "Save",
         "visible": true
      },
      {
         "command": "Concat44",
         "visible": true,
         "matrix": [
            [ 1, 0, 0, 1196 ],
            [ 0, 1, 0, 1370 ],
            [ 0, 0, 1, 0 ],
            [ 0, 0, 0, 1 ]
         ]
      },
      {
         "command": "DrawRRect",
         "visible": true,
         "coords": [ [ 0, 0, 44, 44 ], [ 22, 22 ], [ 22, 22 ], [ 22, 22 ], [ 22, 22 ] ],
         "paint": {
            "antiAlias": true,
            "color": [ 255, 13, 92, 255 ]
         }
      },
      {
         "command": "SaveLayer",
         "visible": true,
         "bounds": [ 11, 11, 33, 34 ],
         "paint": {
            "imagefilter": {
               "name": "SkColorFilterImageFilter",
               "data": "data/1",
               "values": {
                  "00_int": 1,
                  "01_bool": false,
                  "02_SkComposeColorFilter": {
                     "00_SkMatrixColorFilter": {
                        "00_scalarArray": [
                           0.97,
                           0,
                           0,
                           0,
                           0.015,
                           0,
                           0.97,
                           0,
                           0,
                           0.015,
                           0,
                           0,
                           0.97,
                           0,
                           0.015,
                           0,
                           0,
                           0,
                           1,
                           0
                        ],
                        "01_bool": true,
                        "02_bool": true
                     },
                     "01_SkComposeColorFilter": {
                        "00_SkMatrixColorFilter": {
                           "00_scalarArray": [
                              1.16,
                              0,
                              0,
                              0,
                              0,
                              0,
                              1.16,
                              0,
                              0,
                              0,
                              0,
                              0,
                              1.16,
                              0,
                              0,
                              0,
                              0,
                              0,
                              1,
                              0
                           ],
                           "01_bool": true,
                           "02_bool": true
                        },
                        "01_SkComposeColorFilter": {
                           "00_SkMatrixColorFilter": {
                              "00_scalarArray": [
                                 0.314398,
                                 1.52255,
                                 -0.836948,
                                 0,
                                 0,
                                 0.101036,
                                 0.536698,
                                 0.362266,
                                 0,
                                 0,
                                 1.02198,
                                 0.106467,
                                 -0.128452,
                                 0,
                                 0,
                                 0,
                                 0,
                                 0,
                                 1,
                                 0
                              ],
                              "01_bool": true,
                              "02_bool": true
                           },
                           "01_SkComposeColorFilter": {
                              "00_SkMatrixColorFilter": {
                                 "00_scalarArray": [
                                    10.8296,
                                    -8.93035,
                                    -0.899281,
                                    0,
                                    0,
                                    -2.66037,
                                    4.55965,
                                    -0.89928,
                                    0,
                                    0,
                                    -2.66037,
                                    -8.93035,
                                    12.5907,
                                    0,
                                    0,
                                    0,
                                    0,
                                    0,
                                    1,
                                    0
                                 ],
                                 "01_bool": true,
                                 "02_bool": true
                              },
                              "01_SkComposeColorFilter": {
                                 "00_SkMatrixColorFilter": {
                                    "00_scalarArray": [
                                       0.97572,
                                       0.03076,
                                       0.00756,
                                       0,
                                       0,
                                       0.01396,
                                       0.98744,
                                       0.00672001,
                                       0,
                                       0,
                                       0.01088,
                                       0.02136,
                                       0.96524,
                                       0,
                                       0,
                                       0,
                                       0,
                                       0,
                                       1,
                                       0
                                    ],
                                    "01_bool": true,
                                    "02_bool": true
                                 },
                                 "01_SkComposeColorFilter": {
                                    "00_SkMatrixColorFilter": {
                                       "00_scalarArray": [
                                          -0.96,
                                          0,
                                          0,
                                          0,
                                          0.98,
                                          0,
                                          -0.96,
                                          0,
                                          0,
                                          0.98,
                                          0,
                                          0,
                                          -0.96,
                                          0,
                                          0.98,
                                          0,
                                          0,
                                          0,
                                          1,
                                          0
                                       ],
                                       "01_bool": true,
                                       "02_bool": true
                                    },
                                    "01_SkComposeColorFilter": {
                                       "00_SkMatrixColorFilter": {
                                          "00_scalarArray": [
                                             1,
                                             0,
                                             0,
                                             0,
                                             0,
                                             0,
                                             1,
                                             0,
                                             0,
                                             0,
                                             0,
                                             0,
                                             1,
                                             0,
                                             0,
                                             0,
                                             0,
                                             0,
                                             1,
                                             0
                                          ],
                                          "01_bool": true,
                                          "02_bool": true
                                       },
                                       "01_SkMatrixColorFilter": {
                                          "00_scalarArray": [
                                             0,
                                             0,
                                             0,
                                             0,
                                             0,
                                             0,
                                             0,
                                             0,
                                             0,
                                             0,
                                             0,
                                             0,
                                             0,
                                             0,
                                             0,
                                             0,
                                             0,
                                             0,
                                             1,
                                             0
                                          ],
                                          "01_bool": true,
                                          "02_bool": true
                                       }
                                    }
                                 }
                              }
                           }
                        }
                     }
                  }
               }
            }
         }
      },
      {
         "command": "Save",
         "visible": true
      },
      {
         "command": "ClipRect",
         "visible": true,
         "coords": [ 11, 11, 33, 33 ],
         "op": "intersect",
         "antiAlias": false,
         "shortDesc": " [11 11 33 33]"
      },
      {
         "command": "Concat44",
         "visible": true,
         "matrix": [
            [ 1, 0, 0, 11 ],
            [ 0, 1, 0, 11 ],
            [ 0, 0, 1, 0 ],
            [ 0, 0, 0, 1 ]
         ]
      },
      {
         "command": "Save",
         "visible": true
      },
      {
         "command": "ClipRect",
         "visible": true,
         "coords": [ 0, 0, 22, 22 ],
         "op": "intersect",
         "antiAlias": true,
         "shortDesc": " [0 0 22 22]"
      },
      {
         "command": "Save",
         "visible": true
      },
      {
         "command": "Concat44",
         "visible": true,
         "matrix": [
            [ 1.375, 0, 0, 0 ],
            [ 0, 1.375, 0, 0 ],
            [ 0, 0, 1, 0 ],
            [ 0, 0, 0, 1 ]
         ]
      },
      {
         "command": "DrawPath",
         "visible": true,
         "path": {
            "dump": "path.setFillType(SkPathFillType::kEvenOdd);\npath.moveTo(4.89433002f, 0.552733958f);\npath.cubicTo(6.89706993f, 4.55821991f, 9.67547989f, 6.81358004f, 12.5170002f, 6.81358004f);\npath.lineTo(12.5170002f, 8.81357956f);\npath.cubicTo(9.67549038f, 8.81357956f, 6.89706993f, 11.0690002f, 4.89433002f, 15.0745001f);\npath.lineTo(3.10546994f, 14.1801004f);\npath.cubicTo(4.5134902f, 11.3640003f, 6.43132019f, 9.05727959f, 8.71411037f, 7.81359005f);\npath.cubicTo(6.43132019f, 6.56992006f, 4.5134902f, 4.26319981f, 3.10546994f, 1.44716001f);\npath.lineTo(4.89433002f, 0.552733958f);\npath.close();\n",
            "fillType": "evenOdd",
            "verbs": [
               {
                  "move": [ 4.89433, 0.552734 ]
               },
               {
                  "cubic": [
                     [ 6.89707, 4.55822 ],
                     [ 9.67548, 6.81358 ],
                     [ 12.517, 6.81358 ]
                  ]
               },
               {
                  "line": [ 12.517, 8.81358 ]
               },
               {
                  "cubic": [
                     [ 9.67549, 8.81358 ],
                     [ 6.89707, 11.069 ],
                     [ 4.89433, 15.0745 ]
                  ]
               },
               {
                  "line": [ 3.10547, 14.1801 ]
               },
               {
                  "cubic": [
                     [ 4.51349, 11.364 ],
                     [ 6.43132, 9.05728 ],
                     [ 8.71411, 7.81359 ]
                  ]
               },
               {
                  "cubic": [
                     [ 6.43132, 6.56992 ],
                     [ 4.51349, 4.2632 ],
                     [ 3.10547, 1.44716 ]
                  ]
               },
               {
                  "line": [ 4.89433, 0.552734 ]
               },
               "close"
            ]
         },
         "paint": {
            "antiAlias": true
         }
      },
      {
         "command": "Restore",
         "visible": true
      },
      {
         "command": "Restore",
         "visible": true
      },
      {
         "command": "Restore",
         "visible": true
      },
      {
         "command": "Restore",
         "visible": true
      },
      {
         "command": "Restore",
         "visible": true
      },
      {
         "command": "Restore",
         "visible": true
      }
   ]
}